sc.social.like-2.5-py2.7-nspkg.pth
sc/social/like/__init__.py
sc/social/like/config.py
sc/social/like/configure.zcml
sc/social/like/controlpanel.py
sc/social/like/interfaces.py
sc/social/like/logger.py
sc/social/like/profiles.zcml
sc/social/like/setuphandlers.py
sc/social/like/testing.py
sc/social/like/utils.py
sc/social/like/vocabularies.py
sc/social/like/Extensions/Install.py
sc/social/like/Extensions/__init__.py
sc/social/like/browser/__init__.py
sc/social/like/browser/configure.zcml
sc/social/like/browser/helper.py
sc/social/like/browser/socialikes.py
sc/social/like/browser/viewlets.py
sc/social/like/browser/images/ico-sociallike.png
sc/social/like/browser/images/ico-telegram.svg
sc/social/like/browser/images/ico-whatsapp.svg
sc/social/like/browser/images/pin_it_button.png
sc/social/like/browser/images/share-facebook.png
sc/social/like/browser/images/share-gplus.png
sc/social/like/browser/images/share-linkedin.png
sc/social/like/browser/images/share-twitter.png
sc/social/like/browser/scripts/social_like.js
sc/social/like/browser/stylesheets/social_like.css
sc/social/like/browser/templates/metadata.pt
sc/social/like/browser/templates/sociallikes.pt
sc/social/like/locales/manual.pot
sc/social/like/locales/plone.pot
sc/social/like/locales/rebuildPo.sh
sc/social/like/locales/sc.social.like.pot
sc/social/like/locales/de/LC_MESSAGES/sc.social.like.po
sc/social/like/locales/es/LC_MESSAGES/sc.social.like.po
sc/social/like/locales/eu/LC_MESSAGES/sc.social.like.po
sc/social/like/locales/it/LC_MESSAGES/sc.social.like.po
sc/social/like/locales/nl/LC_MESSAGES/sc.social.like.po
sc/social/like/locales/pt_BR/LC_MESSAGES/sc.social.like.po
sc/social/like/plugins/__init__.py
sc/social/like/plugins/configure.zcml
sc/social/like/plugins/interfaces.py
sc/social/like/plugins/facebook/__init__.py
sc/social/like/plugins/facebook/browser.py
sc/social/like/plugins/facebook/config.py
sc/social/like/plugins/facebook/configure.zcml
sc.social.like-2.5.dist-info/DESCRIPTION.rst
sc.social.like-2.5.dist-info/METADATA
sc.social.like-2.5.dist-info/RECORD
sc.social.like-2.5.dist-info/WHEEL
sc.social.like-2.5.dist-info/entry_points.txt
sc.social.like-2.5.dist-info/metadata.json
sc.social.like-2.5.dist-info/namespace_packages.txt
sc.social.like-2.5.dist-info/top_level.txt
