Metadata-Version: 2.0
Name: sc.social.like
Version: 2.5
Summary: Social Like is a Plone package providing simple Google+,
Home-page: https://github.com/collective/sc.social.like
Author: Simples Consultoria
Author-email: products@simplesconsultoria.com.br
License: GPLv2
Keywords: python plone zope webdev social googleplus facebook twitter
Platform: UNKNOWN
Classifier: Development Status :: 5 - Production/Stable
Classifier: Environment :: Web Environment
Classifier: Framework :: Plone
Classifier: Framework :: Plone :: 4.2
Classifier: Framework :: Plone :: 4.3
Classifier: Intended Audience :: End Users/Desktop
Classifier: Intended Audience :: System Administrators
Classifier: License :: OSI Approved :: GNU General Public License v2 (GPLv2)
Classifier: Operating System :: OS Independent
Classifier: Programming Language :: JavaScript
Classifier: Programming Language :: Python
Classifier: Programming Language :: Python :: 2.7
Classifier: Topic :: Office/Business :: News/Diary
Classifier: Topic :: Software Development :: Libraries :: Python Modules
Requires-Dist: Acquisition
Requires-Dist: Products.Archetypes
Requires-Dist: Products.CMFCore
Requires-Dist: Products.CMFDefault
Requires-Dist: Products.CMFPlone (>=4.2)
Requires-Dist: Products.CMFQuickInstallerTool
Requires-Dist: Products.GenericSetup
Requires-Dist: plone.api
Requires-Dist: plone.app.layout
Requires-Dist: plone.app.registry
Requires-Dist: plone.app.upgrade
Requires-Dist: plone.memoize
Requires-Dist: plone.registry
Requires-Dist: plone.supermodel
Requires-Dist: setuptools
Requires-Dist: zope.component
Requires-Dist: zope.i18nmessageid
Requires-Dist: zope.interface
Requires-Dist: zope.schema
Provides-Extra: develop
Requires-Dist: docutils; extra == 'develop'
Provides-Extra: test
Requires-Dist: plone.app.robotframework; extra == 'test'
Requires-Dist: plone.app.testing[robot] (>=4.2.2); extra == 'test'
Requires-Dist: plone.browserlayer; extra == 'test'
Requires-Dist: robotsuite; extra == 'test'
